mnemo_lib/__init__.py
mnemo_lib/constants.py
mnemo_lib/intbuffer.py
mnemo_lib/models.py
mnemo_lib/utils.py
mnemo_lib/commands/__init__.py
mnemo_lib/commands/convert.py
mnemo_lib/commands/correct.py
mnemo_lib/commands/main.py
mnemo_lib/commands/split.py
mnemo_lib-0.0.7.dist-info/entry_points.txt
mnemo_lib-0.0.7.dist-info/licenses/LICENSE
mnemo_lib-0.0.7.dist-info/WHEEL
mnemo_lib-0.0.7.dist-info/METADATA
mnemo_lib-0.0.7.dist-info/RECORD
